spear/__init__.py
spear/Implyloss/__init__.py
spear/Implyloss/checkmate.py
spear/Implyloss/checkpoints.py
spear/Implyloss/data_feeder_utils.py
spear/Implyloss/data_feeders.py
spear/Implyloss/data_types.py
spear/Implyloss/gen_cross_entropy_utils.py
spear/Implyloss/main.py
spear/Implyloss/model.py
spear/Implyloss/networks.py
spear/Implyloss/pr_utils.py
spear/Implyloss/test.py
spear/Implyloss/train.py
spear/Implyloss/utils.py
spear/cage/__init__.py
spear/cage/core.py
spear/jl/__init__.py
spear/jl/core.py
spear/jl/subset_selection.py
spear/jl/models/__init__.py
spear/jl/models/models.py
spear/labeling/__init__.py
spear/labeling/analysis/__init__.py
spear/labeling/analysis/core.py
spear/labeling/apply/__init__.py
spear/labeling/apply/core.py
spear/labeling/continuous_scoring/__init__.py
spear/labeling/continuous_scoring/core.py
spear/labeling/data_types/__init__.py
spear/labeling/data_types/data.py
spear/labeling/lf/__init__.py
spear/labeling/lf/core.py
spear/labeling/lf_set/__init__.py
spear/labeling/lf_set/core.py
spear/labeling/prelabels/__init__.py
spear/labeling/prelabels/core.py
spear/labeling/preprocess/__init__.py
spear/labeling/preprocess/core.py
spear/labeling/utils/__init__.py
spear/labeling/utils/data_operators.py
spear/labeling/utils/pickle.py
spear/labeling/utils/plot.py
spear/utils/__init__.py
spear/utils/data_editor.py
spear/utils/utils_cage.py
spear/utils/utils_jl.py
decile_spear-1.0.8.dist-info/LICENSE.txt
decile_spear-1.0.8.dist-info/METADATA
decile_spear-1.0.8.dist-info/WHEEL
decile_spear-1.0.8.dist-info/top_level.txt
decile_spear-1.0.8.dist-info/RECORD
